transparentmeta/__init__.py
transparentmeta/crypto/__init__.py
transparentmeta/crypto/character_encoding.py
transparentmeta/crypto/exceptions.py
transparentmeta/crypto/hasher.py
transparentmeta/crypto/key_management.py
transparentmeta/crypto/signature_verifier.py
transparentmeta/crypto/signer.py
transparentmeta/entity/__init__.py
transparentmeta/entity/metadata.py
transparentmeta/logger_config.py
transparentmeta/request/__init__.py
transparentmeta/request/exceptions.py
transparentmeta/request/file_validators.py
transparentmeta/request/read_request.py
transparentmeta/request/write_request.py
transparentmeta/result/__init__.py
transparentmeta/result/result.py
transparentmeta/sdk/__init__.py
transparentmeta/sdk/factory.py
transparentmeta/sdk/transparent_metadata_reader.py
transparentmeta/sdk/transparent_metadata_writer.py
transparentmeta/serialization/__init__.py
transparentmeta/serialization/metadata_serializer.py
transparentmeta/use_case/__init__.py
transparentmeta/use_case/constants.py
transparentmeta/use_case/exceptions.py
transparentmeta/use_case/read/__init__.py
transparentmeta/use_case/read/factory.py
transparentmeta/use_case/read/metadata_reader.py
transparentmeta/use_case/read/mp3_metadata_reader.py
transparentmeta/use_case/read/read_use_case.py
transparentmeta/use_case/read/reader_selector.py
transparentmeta/use_case/read/wav_metadata_reader.py
transparentmeta/use_case/types.py
transparentmeta/use_case/write/__init__.py
transparentmeta/use_case/write/factory.py
transparentmeta/use_case/write/metadata_writer.py
transparentmeta/use_case/write/mp3_metadata_writer.py
transparentmeta/use_case/write/wav_metadata_writer.py
transparentmeta/use_case/write/write_use_case.py
transparentmeta/use_case/write/writer_selector.py
transparentmeta/utils/__init__.py
transparentmeta/utils/encoding_utils.py
transparentmeta/utils/exceptions.py
transparentmeta/utils/file_utils.py
transparentmeta/utils/metadata_tags_utils.py
transparentmeta-1.0.0.dist-info/LICENSE
transparentmeta-1.0.0.dist-info/METADATA
transparentmeta-1.0.0.dist-info/WHEEL
transparentmeta-1.0.0.dist-info/RECORD
