Metadata-Version: 2.3
Name: transparentmeta
Version: 1.0.0
Summary: Python library to write, read, and verify transparency metadata in audio files for AI transparency compliance.
License: GPL-3.0-or-later
Author: Valerio Velardo
Author-email: valerio@transparentaudio.ai
Requires-Python: >=3.12,<4.0
Classifier: License :: OSI Approved :: GNU General Public License v3 or later (GPLv3+)
Classifier: Programming Language :: Python :: 3
Classifier: Programming Language :: Python :: 3.12
Classifier: Programming Language :: Python :: 3.13
Requires-Dist: cryptography (==44.0.1)
Requires-Dist: mutagen (==1.47.0)
Requires-Dist: pydantic (==2.10.6)
